arcade_freshservice_api/__init__.py
arcade_freshservice_api/moar/Freshservice.json
arcade_freshservice_api/moar/openapi.json
arcade_freshservice_api/tools/__init__.py
arcade_freshservice_api/tools/request_body_schemas.py
arcade_freshservice_api/wrapper_tools/ActivateCsatSurvey.json
arcade_freshservice_api/wrapper_tools/AddAssetComponent.json
arcade_freshservice_api/wrapper_tools/AddNoteToProblem.json
arcade_freshservice_api/wrapper_tools/AddReleaseNote.json
arcade_freshservice_api/wrapper_tools/AddReleaseTimeEntry.json
arcade_freshservice_api/wrapper_tools/AddTicketNote.json
arcade_freshservice_api/wrapper_tools/ArchiveProject.json
arcade_freshservice_api/wrapper_tools/ConvertAgentToRequester.json
arcade_freshservice_api/wrapper_tools/ConvertRequesterToAgent.json
arcade_freshservice_api/wrapper_tools/CreateAgentGroupFreshservice.json
arcade_freshservice_api/wrapper_tools/CreateAnnouncement.json
arcade_freshservice_api/wrapper_tools/CreateAssetType.json
arcade_freshservice_api/wrapper_tools/CreateCannedResponseFolder.json
arcade_freshservice_api/wrapper_tools/CreateChangeNote.json
arcade_freshservice_api/wrapper_tools/CreateChangeTask.json
arcade_freshservice_api/wrapper_tools/CreateChildTicket.json
arcade_freshservice_api/wrapper_tools/CreateCsatSurvey.json
arcade_freshservice_api/wrapper_tools/CreateCustomTicketSource.json
arcade_freshservice_api/wrapper_tools/CreateFreshserviceAgent.json
arcade_freshservice_api/wrapper_tools/CreateFreshserviceCannedResponse.json
arcade_freshservice_api/wrapper_tools/CreateFreshserviceChangeRequest.json
arcade_freshservice_api/wrapper_tools/CreateFreshserviceChangeTimeEntry.json
arcade_freshservice_api/wrapper_tools/CreateFreshserviceProblemTask.json
arcade_freshservice_api/wrapper_tools/CreateFreshserviceProject.json
arcade_freshservice_api/wrapper_tools/CreateFreshserviceTicket.json
arcade_freshservice_api/wrapper_tools/CreateNewAsset.json
arcade_freshservice_api/wrapper_tools/CreateNewLocation.json
arcade_freshservice_api-3.0.0.dist-info/METADATA
arcade_freshservice_api-3.0.0.dist-info/WHEEL
arcade_freshservice_api-3.0.0.dist-info/entry_points.txt
arcade_freshservice_api-3.0.0.dist-info/licenses/LICENSE
arcade_freshservice_api-3.0.0.dist-info/RECORD
